stronghold/__init__.py
stronghold/conf.py
stronghold/decorators.py
stronghold/middleware.py
stronghold/models.py
stronghold/utils.py
stronghold/views.py
stronghold/tests/__init__.py
stronghold/tests/testdecorators.py
stronghold/tests/testmiddleware.py
stronghold/tests/testmixins.py
stronghold/tests/testutils.py
django_stronghold-0.3.2.dist-info/LICENSE
django_stronghold-0.3.2.dist-info/METADATA
django_stronghold-0.3.2.dist-info/WHEEL
django_stronghold-0.3.2.dist-info/top_level.txt
django_stronghold-0.3.2.dist-info/RECORD
