Metadata-Version: 2.1
Name: django-stronghold
Version: 0.3.2
Summary: Get inside your stronghold and make all your Django views default login_required
Home-page: https://github.com/mgrouchy/django-stronghold
Author: Mike Grouchy
Author-email: mgrouchy@gmail.com
License: MIT license
Platform: UNKNOWN
Classifier: Development Status :: 5 - Production/Stable
Classifier: Intended Audience :: Developers
Classifier: Natural Language :: English
Classifier: License :: OSI Approved :: MIT License
Classifier: Programming Language :: Python
Classifier: Programming Language :: Python :: 2.7
Classifier: Programming Language :: Python :: 3
Classifier: Programming Language :: Python :: 3.4
Classifier: Programming Language :: Python :: 3.5
Classifier: Programming Language :: Python :: 3.6
Classifier: Programming Language :: Python :: 3.7
